aimlflow/AiService.py
aimlflow/__init__.py
aimlflow/constants.py
aimlflow/utils.py
aimlflow-1.0.0.dist-info/LICENSE
aimlflow-1.0.0.dist-info/METADATA
aimlflow-1.0.0.dist-info/WHEEL
aimlflow-1.0.0.dist-info/top_level.txt
aimlflow-1.0.0.dist-info/RECORD
