Metadata-Version: 2.1
Name: aimlflow
Version: 1.0.0
Summary: Python Client to access Navigator
Home-page: https://navigator.pyxeda.ai
Author: Pyxeda AI
Author-email: support@pyxeda.ai
License: UNKNOWN
Platform: UNKNOWN
Classifier: Programming Language :: Python :: 3
Classifier: License :: OSI Approved :: MIT License
Classifier: Operating System :: OS Independent
Requires-Python: >=3.6
Requires-Dist: colorama
Requires-Dist: numpy
Requires-Dist: pandas
Requires-Dist: requests
Requires-Dist: requests-oauthlib
Requires-Dist: requests-toolbelt
Requires-Dist: termcolor (==1.1.0)
Requires-Dist: twine
Requires-Dist: urllib3
